jaraco/xkcd.py
jaraco.xkcd-3.0.3.dist-info/LICENSE
jaraco.xkcd-3.0.3.dist-info/METADATA
jaraco.xkcd-3.0.3.dist-info/WHEEL
jaraco.xkcd-3.0.3.dist-info/top_level.txt
jaraco.xkcd-3.0.3.dist-info/RECORD
